MANIFEST.in
README.rst
setup.py
pydtw/__init__.py
pydtw/dtw.pyx
test/__init__.py
test/test_dtw.py