Metadata-Version: 1.1
Name: pydtw
Version: 1.0.0
Summary: Fast Imprementation of the Dynamic Wime Warping
Home-page: https://github.com/shunsukeaihara/pydtw
Author: Shunsuke Aihara
Author-email: aihara@argmax.jp
License: MIT License
Platform: UNKNOWN
Classifier: Programming Language :: Python
Classifier: Programming Language :: Python :: 3
Classifier: Programming Language :: Python :: 2
